meldrx_fhir_client/FHIRClient.py
meldrx_fhir_client/__init__.py
tests/__init__.py
tests/test_FHIRClient.py
meldrx_fhir_client-0.0.8.dist-info/METADATA
meldrx_fhir_client-0.0.8.dist-info/WHEEL
meldrx_fhir_client-0.0.8.dist-info/top_level.txt
meldrx_fhir_client-0.0.8.dist-info/RECORD
