Metadata-Version: 2.1
Name: meldrx_fhir_client
Version: 0.0.8
Summary: A simple FHIR client for MeldRX.
Home-page: https://github.com/darena-solutions/meldrx-client-py
Author: EM
Author-email: eric@darenasolutions.com
License: MIT
Classifier: Intended Audience :: Developers
Classifier: License :: OSI Approved :: MIT License
Classifier: Programming Language :: Python :: 3.7
Classifier: Programming Language :: Python :: 3.8
Classifier: Programming Language :: Python :: 3.9
Classifier: Programming Language :: Python :: 3.10
Classifier: Topic :: Software Development :: Libraries :: Python Modules
